{
  "app": {
    "signingConfigs": [
      {
        "name": "default",
        "type": "HarmonyOS",
        "material": {
          "certpath": "C:\\Users\\wangtao\\.ohos\\config\\auto_debug_lemon_site.shuangchen.lemon_160086200300216203.cer",
          "storePassword": "0000001AB7EB23CC044984A81274FAA91852B0137F6CCDA12724ED8264F8F29E979706045CE9EA2D79EF",
          "keyAlias": "debugKey",
          "keyPassword": "0000001A9C032A6CEED5B663CEDCDAF3860EC8D310CB4A5ACD0CED175CF47C21C8EC0F90582AF6EE4941",
          "profile": "C:\\Users\\wangtao\\.ohos\\config\\auto_debug_lemon_site.shuangchen.lemon_160086200300216203.p7b",
          "signAlg": "SHA256withECDSA",
          "storeFile": "C:\\Users\\wangtao\\.ohos\\config\\auto_debug_lemon_site.shuangchen.lemon_160086200300216203.p12"
        }
      }
    ],
    "compileSdkVersion": 9,
    "compatibleSdkVersion": 9,
    "products": [
      {
        "name": "default",
        "signingConfig": "default",
      }
    ],
    "buildModeSet": [
      {
        "name": "debug",
      },
      {
        "name": "release"
      }
    ]
  },
  "modules": [
    {
      "name": "entry",
      "srcPath": "./entry",
      "targets": [
        {
          "name": "default",
          "applyToProducts": [
            "default"
          ]
        }
      ]
    }
  ]
}